pyuni/__init__.py
pyuni/client.py
pyuni/exceptions.py
pyuni/university.py
pyuni/objects/__init__.py
pyuni/objects/subject.py
pyuni/scraper/__init__.py
pyuni/scraper/scraper.py
pyuni/scraper/university_scraper/__init__.py
pyuni/scraper/university_scraper/university_of_melbourne_scraper.py
pyuni/scraper/university_scraper/university_scraper.py
pyuni-0.0.4.dist-info/LICENSE
pyuni-0.0.4.dist-info/METADATA
pyuni-0.0.4.dist-info/WHEEL
pyuni-0.0.4.dist-info/top_level.txt
pyuni-0.0.4.dist-info/RECORD
