Metadata-Version: 2.1
Name: pyuni
Version: 0.0.4
Summary: A tool to get classes timetable
Home-page: https://github.com/anhphamduy/pyuni
Author: Anh Pham
Author-email: anhphamduy@outlook.com
License: UNKNOWN
Platform: UNKNOWN
Requires-Python: >=3.6
Requires-Dist: selenium
